livescore/Livescore2017.py
livescore/Livescore2018.py
livescore/Livescore2019.py
livescore/Livescore2020.py
livescore/Livescore2021.py
livescore/Livescore2022.py
livescore/LivescoreBase.py
livescore/LivescoreCommon.py
livescore/__init__.py
livescore/details.py
livescore/simpleocr_utils/__init__.py
livescore/simpleocr_utils/feature_extraction.py
livescore/simpleocr_utils/numpy_utils.py
livescore/simpleocr_utils/opencv_utils.py
livescore/simpleocr_utils/processor.py
livescore/simpleocr_utils/segmentation.py
livescore/simpleocr_utils/segmentation_aux.py
livescore/simpleocr_utils/segmentation_filters.py
livescore/templates/2018_boost.png
livescore/templates/2018_force.png
livescore/templates/2018_levitate.png
livescore/templates/match_results_2022-hires.png
livescore/templates/match_results_2022.png
livescore/templates/score_overlay_2017.png
livescore/templates/score_overlay_2018.png
livescore/templates/score_overlay_2019.png
livescore/templates/score_overlay_2020.png
livescore/templates/score_overlay_2021-hidef.png
livescore/templates/score_overlay_2021.png
livescore/templates/score_overlay_2022-hires.png
livescore/templates/score_overlay_2022.png
livescore/tessdata/digits.traineddata
livescore/tessdata/eng.traineddata
livescore/training_data/digits.pkl
frc_livescore_ng-0.0.1rc110.dist-info/LICENSE
frc_livescore_ng-0.0.1rc110.dist-info/METADATA
frc_livescore_ng-0.0.1rc110.dist-info/WHEEL
frc_livescore_ng-0.0.1rc110.dist-info/top_level.txt
frc_livescore_ng-0.0.1rc110.dist-info/RECORD
