Metadata-Version: 2.1
Name: frc-livescore-ng
Version: 0.0.1rc110
Summary: Get FRC scores from an image
Home-page: https://github.com/TechplexEngineer/frc-livescore
Author: Blake Bourque
License: MIT
Keywords: frc,score,robotics
Platform: UNKNOWN
License-File: LICENSE
Requires-Dist: pytesseract (==0.3.9)
Requires-Dist: numpy (>=1.14.0)
Requires-Dist: regex (==2022.3.2)
Requires-Dist: pyyaml (==6.0)
Requires-Dist: opencv-python (==4.5.5.64)
Requires-Dist: opencv-contrib-python (==4.5.5.64)
Requires-Dist: Pillow (==9.0.1)
